{
    "version": 2,
    "name": "KonKoe",
    "title": "KonKoe",
    "data": [
        {
            "uid": 444015421,
            "room": 21509764,
            "name": "哀嗣",
            "group": "KonKoe",
            "description": "嘿！！ 我是KonKoeProject的哀嗣, 不是企鹅是人类desu",
            "face": "https://i1.hdslb.com/bfs/face/16983c9e8d1f694160a01ec6456467481a83436d.jpg"
        },
        {
            "uid": 808682,
            "room": 506849,
            "name": "海猫umi",
            "group": "KonKoe",
            "description": "私は誰？",
            "face": "https://i2.hdslb.com/bfs/face/d0ce2fb00843c0eb686bfe5f900315880bc8e53a.jpg"
        },
        {
            "uid": 315830968,
            "room": 21240069,
            "name": "眠叶绀Channel",
            "group": "KonKoe",
            "description": "家道中落的社畜大小姐就是本小姐啦！粉丝群：732477414",
            "face": "https://i1.hdslb.com/bfs/face/4b3f0a4084c44af1f5ca4c93df2d70280b913c45.jpg"
        },
        {
            "uid": 38728593,
            "room": 5789579,
            "name": "禾树ki_Channel",
            "group": "KonKoe",
            "description": "KonKoe Project 所属VUP‖今天的情报屋也在学做人x‖情报站：263553107",
            "face": "https://i0.hdslb.com/bfs/face/7570df90d5fe51c4daa5359320209bc360c012e3.jpg"
        },
        {
            "uid": 640418942,
            "room": 22508827,
            "name": "驿双Ethan_Channel",
            "group": "KonKoe",
            "description": "<KonKoe Project所属>热爱生活，做自己喜欢的事情。感谢关注，出道准备中，欢迎与我互动|･ω･｀)\n爱发电：不想做作业",
            "face": "https://i2.hdslb.com/bfs/face/886568380fbcf26683fc1b5a73fe05507d46916b.jpg"
        }
    ]
}