{
    "version": 3,
    "name": "Pursue-live",
    "title": "Pursue-live",
    "data": [
        {
            "uid": 1968342232,
            "room": 24538373,
            "name": "曲奇Aria",
            "group": "Pursue-live",
            "description": "个人势！魔王 狼 /群866343049/录播@狼堡日常记录/",
            "face": "https://i1.hdslb.com/bfs/face/cf62a661436dde7841ea2055d2507eb7eb0d65cc.jpg"
        },
        {
            "uid": 1490293424,
            "room": 25146115,
            "name": "涅涅nene",
            "group": "Pursue-live",
            "description": "【已毕业】转生成妈妈的一名路过猎人～祝孩子们天天开心❤️",
            "face": "https://i2.hdslb.com/bfs/face/16b1e1d3b8614ce0321506bf62b587303edb3051.jpg"
        },
        {
            "uid": 1319590030,
            "room": 24037998,
            "name": "Pisdo皮斯多",
            "group": "Pursue-live",
            "description": "^ ^ \n‹Pursue-live›",
            "face": "https://i1.hdslb.com/bfs/face/eab0b32512b018d141d9de0e60c0676e080aeb79.jpg"
        }
    ]
}